gsee/__init__.py
gsee/brl_model.py
gsee/cec_tools.py
gsee/pv.py
gsee/trigon.py
gsee/climatedata_interface/__init__.py
gsee/climatedata_interface/generate_pdfs.py
gsee/climatedata_interface/interface.py
gsee/climatedata_interface/kt_h_sinusfunc.c
gsee/climatedata_interface/kt_h_sinusfunc.cpython-310-darwin.so
gsee/climatedata_interface/kt_h_sinusfunc.pyx
gsee/climatedata_interface/pre_gsee_processing.py
gsee/climatedata_interface/progress.py
gsee/climatedata_interface/util.py
gsee_redux-0.4.0.dev0.dist-info/LICENSE
gsee_redux-0.4.0.dev0.dist-info/METADATA
gsee_redux-0.4.0.dev0.dist-info/WHEEL
gsee_redux-0.4.0.dev0.dist-info/top_level.txt
gsee_redux-0.4.0.dev0.dist-info/RECORD
