Metadata-Version: 2.1
Name: gsee-redux
Version: 0.4.0.dev0
Summary: GSEE: Global Solar Energy Estimator
Home-page: https://github.com/scene-connect/gsee-redux
Author: ZUoS Ltd
Author-email: info@zuos.co.uk
License: BSD 3-Clause License
Project-URL: Repository, https://github.com/scene-connect/gsee-redux
Platform: UNKNOWN
Classifier: Development Status :: 5 - Production/Stable
Classifier: Intended Audience :: Developers
Classifier: Intended Audience :: Science/Research
Classifier: License :: OSI Approved :: BSD License
Classifier: Programming Language :: Cython
Classifier: Programming Language :: Python
Classifier: Programming Language :: Python :: 3
Classifier: Programming Language :: Python :: 3 :: Only
Classifier: Programming Language :: Python :: 3.7
Classifier: Programming Language :: Python :: 3.8
Classifier: Programming Language :: Python :: 3.9
Classifier: Programming Language :: Python :: 3.10
Classifier: Topic :: Scientific/Engineering
Requires-Python: >=3
License-File: LICENSE
Requires-Dist: joblib (>=0.12)
Requires-Dist: numpy (>=1.15.0)
Requires-Dist: pandas (>=1.0)
Requires-Dist: pvlib (>=0.6.3)
Requires-Dist: pyephem (>=3.7.6)
Requires-Dist: scipy (>=1.1.0)
Requires-Dist: xarray[parallel] (>=0.16)
Provides-Extra: generate_pdfs
Requires-Dist: basemap (>=1.1.0) ; extra == 'generate_pdfs'
Requires-Dist: seaborn (>=0.9.0) ; extra == 'generate_pdfs'
